rlm/__init__.py
rlm/cli.py
rlm/config.py
rlm/core.py
rlm/fast_rlm.py
rlm/logging_config.py
rlm/parser.py
rlm/prompts.py
rlm/repl.py
rlm/scalable_rlm.py
rlm/server.py
rlm/streaming.py
rlm/clients/__init__.py
rlm/clients/anthropic_client.py
rlm/clients/base.py
rlm/clients/openai_client.py
rlm/optimizations/__init__.py
rlm/optimizations/batching.py
rlm/optimizations/caching.py
rlm/optimizations/chunking.py
rlm/optimizations/speed.py
rlm_engine-1.0.0.dist-info/METADATA
rlm_engine-1.0.0.dist-info/WHEEL
rlm_engine-1.0.0.dist-info/entry_points.txt
rlm_engine-1.0.0.dist-info/top_level.txt
rlm_engine-1.0.0.dist-info/RECORD
