Metadata-Version: 2.4
Name: rlm-engine
Version: 1.0.0
Summary: Recursive Language Model - Process unlimited context with any LLM
Author-email: RLM Team <rlm@example.com>
License: MIT
Project-URL: Homepage, https://github.com/rlm-engine/rlm-engine
Project-URL: Documentation, https://github.com/rlm-engine/rlm-engine#readme
Project-URL: Repository, https://github.com/rlm-engine/rlm-engine
Keywords: llm,rlm,recursive,language-model,vllm,openai,context,nlp
Classifier: Development Status :: 4 - Beta
Classifier: Intended Audience :: Developers
Classifier: Intended Audience :: Science/Research
Classifier: License :: OSI Approved :: MIT License
Classifier: Programming Language :: Python :: 3
Classifier: Programming Language :: Python :: 3.10
Classifier: Programming Language :: Python :: 3.11
Classifier: Programming Language :: Python :: 3.12
Classifier: Topic :: Scientific/Engineering :: Artificial Intelligence
Classifier: Topic :: Text Processing :: General
Requires-Python: >=3.10
Requires-Dist: httpx[http2]>=0.25.0
Requires-Dist: openai>=1.0.0
Requires-Dist: anthropic>=0.20.0
Requires-Dist: python-dotenv>=1.0.0
Provides-Extra: dev
Requires-Dist: pytest>=7.0.0; extra == "dev"
Requires-Dist: pytest-asyncio>=0.21.0; extra == "dev"
Requires-Dist: pytest-cov>=4.0.0; extra == "dev"
Requires-Dist: build>=1.0.0; extra == "dev"
Requires-Dist: twine>=4.0.0; extra == "dev"
Provides-Extra: server
Requires-Dist: fastapi>=0.100.0; extra == "server"
Requires-Dist: uvicorn>=0.23.0; extra == "server"
Provides-Extra: config
Requires-Dist: pyyaml>=6.0; extra == "config"
Provides-Extra: all
Requires-Dist: rlm-engine[config,dev,server]; extra == "all"
